{
  "openapi": "3.0.4",
  "info": {
    "title": "BankCustomerApi",
    "version": "v1"
  },
  "paths": {
    "/api/Account": {
      "get": {
        "tags": [
          "Account"
        ],
        "responses": {
          "200": {
            "description": "OK",
            "content": {
              "text/plain": {
                "schema": {
                  "type": "array",
                  "items": {
                    "$ref": "#/components/schemas/Account"
                  }
                }
              },
              "application/json": {
                "schema": {
                  "type": "array",
                  "items": {
                    "$ref": "#/components/schemas/Account"
                  }
                }
              },
              "text/json": {
                "schema": {
                  "type": "array",
                  "items": {
                    "$ref": "#/components/schemas/Account"
                  }
                }
              }
            }
          }
        }
      },
      "post": {
        "tags": [
          "Account"
        ],
        "requestBody": {
          "content": {
            "application/json": {
              "schema": {
                "$ref": "#/components/schemas/Account"
              }
            },
            "text/json": {
              "schema": {
                "$ref": "#/components/schemas/Account"
              }
            },
            "application/*+json": {
              "schema": {
                "$ref": "#/components/schemas/Account"
              }
            }
          }
        },
        "responses": {
          "200": {
            "description": "OK",
            "content": {
              "text/plain": {
                "schema": {
                  "$ref": "#/components/schemas/Account"
                }
              },
              "application/json": {
                "schema": {
                  "$ref": "#/components/schemas/Account"
                }
              },
              "text/json": {
                "schema": {
                  "$ref": "#/components/schemas/Account"
                }
              }
            }
          }
        }
      }
    },
    "/api/Account/{id}": {
      "get": {
        "tags": [
          "Account"
        ],
        "parameters": [
          {
            "name": "id",
            "in": "path",
            "required": true,
            "schema": {
              "type": "integer",
              "format": "int32"
            }
          }
        ],
        "responses": {
          "200": {
            "description": "OK",
            "content": {
              "text/plain": {
                "schema": {
                  "$ref": "#/components/schemas/Account"
                }
              },
              "application/json": {
                "schema": {
                  "$ref": "#/components/schemas/Account"
                }
              },
              "text/json": {
                "schema": {
                  "$ref": "#/components/schemas/Account"
                }
              }
            }
          }
        }
      },
      "put": {
        "tags": [
          "Account"
        ],
        "parameters": [
          {
            "name": "id",
            "in": "path",
            "required": true,
            "schema": {
              "type": "integer",
              "format": "int32"
            }
          }
        ],
        "requestBody": {
          "content": {
            "application/json": {
              "schema": {
                "$ref": "#/components/schemas/Account"
              }
            },
            "text/json": {
              "schema": {
                "$ref": "#/components/schemas/Account"
              }
            },
            "application/*+json": {
              "schema": {
                "$ref": "#/components/schemas/Account"
              }
            }
          }
        },
        "responses": {
          "200": {
            "description": "OK"
          }
        }
      },
      "delete": {
        "tags": [
          "Account"
        ],
        "parameters": [
          {
            "name": "id",
            "in": "path",
            "required": true,
            "schema": {
              "type": "integer",
              "format": "int32"
            }
          }
        ],
        "responses": {
          "200": {
            "description": "OK"
          }
        }
      }
    },
    "/api/Auth/login": {
      "post": {
        "tags": [
          "Auth"
        ],
        "requestBody": {
          "content": {
            "application/json": {
              "schema": {
                "$ref": "#/components/schemas/LoginRequest"
              }
            },
            "text/json": {
              "schema": {
                "$ref": "#/components/schemas/LoginRequest"
              }
            },
            "application/*+json": {
              "schema": {
                "$ref": "#/components/schemas/LoginRequest"
              }
            }
          }
        },
        "responses": {
          "200": {
            "description": "OK"
          }
        }
      }
    },
    "/api/Bank": {
      "get": {
        "tags": [
          "Bank"
        ],
        "responses": {
          "200": {
            "description": "OK",
            "content": {
              "text/plain": {
                "schema": {
                  "type": "array",
                  "items": {
                    "$ref": "#/components/schemas/Bank"
                  }
                }
              },
              "application/json": {
                "schema": {
                  "type": "array",
                  "items": {
                    "$ref": "#/components/schemas/Bank"
                  }
                }
              },
              "text/json": {
                "schema": {
                  "type": "array",
                  "items": {
                    "$ref": "#/components/schemas/Bank"
                  }
                }
              }
            }
          }
        }
      },
      "post": {
        "tags": [
          "Bank"
        ],
        "requestBody": {
          "content": {
            "application/json": {
              "schema": {
                "$ref": "#/components/schemas/Bank"
              }
            },
            "text/json": {
              "schema": {
                "$ref": "#/components/schemas/Bank"
              }
            },
            "application/*+json": {
              "schema": {
                "$ref": "#/components/schemas/Bank"
              }
            }
          }
        },
        "responses": {
          "200": {
            "description": "OK",
            "content": {
              "text/plain": {
                "schema": {
                  "$ref": "#/components/schemas/Bank"
                }
              },
              "application/json": {
                "schema": {
                  "$ref": "#/components/schemas/Bank"
                }
              },
              "text/json": {
                "schema": {
                  "$ref": "#/components/schemas/Bank"
                }
              }
            }
          }
        }
      }
    },
    "/api/Bank/{id}": {
      "get": {
        "tags": [
          "Bank"
        ],
        "parameters": [
          {
            "name": "id",
            "in": "path",
            "required": true,
            "schema": {
              "type": "integer",
              "format": "int32"
            }
          }
        ],
        "responses": {
          "200": {
            "description": "OK",
            "content": {
              "text/plain": {
                "schema": {
                  "$ref": "#/components/schemas/Bank"
                }
              },
              "application/json": {
                "schema": {
                  "$ref": "#/components/schemas/Bank"
                }
              },
              "text/json": {
                "schema": {
                  "$ref": "#/components/schemas/Bank"
                }
              }
            }
          }
        }
      },
      "put": {
        "tags": [
          "Bank"
        ],
        "parameters": [
          {
            "name": "id",
            "in": "path",
            "required": true,
            "schema": {
              "type": "integer",
              "format": "int32"
            }
          }
        ],
        "requestBody": {
          "content": {
            "application/json": {
              "schema": {
                "$ref": "#/components/schemas/Bank"
              }
            },
            "text/json": {
              "schema": {
                "$ref": "#/components/schemas/Bank"
              }
            },
            "application/*+json": {
              "schema": {
                "$ref": "#/components/schemas/Bank"
              }
            }
          }
        },
        "responses": {
          "200": {
            "description": "OK"
          }
        }
      },
      "delete": {
        "tags": [
          "Bank"
        ],
        "parameters": [
          {
            "name": "id",
            "in": "path",
            "required": true,
            "schema": {
              "type": "integer",
              "format": "int32"
            }
          }
        ],
        "responses": {
          "200": {
            "description": "OK"
          }
        }
      }
    },
    "/api/Branch": {
      "get": {
        "tags": [
          "Branch"
        ],
        "responses": {
          "200": {
            "description": "OK",
            "content": {
              "text/plain": {
                "schema": {
                  "type": "array",
                  "items": {
                    "$ref": "#/components/schemas/Branch"
                  }
                }
              },
              "application/json": {
                "schema": {
                  "type": "array",
                  "items": {
                    "$ref": "#/components/schemas/Branch"
                  }
                }
              },
              "text/json": {
                "schema": {
                  "type": "array",
                  "items": {
                    "$ref": "#/components/schemas/Branch"
                  }
                }
              }
            }
          }
        }
      },
      "post": {
        "tags": [
          "Branch"
        ],
        "requestBody": {
          "content": {
            "application/json": {
              "schema": {
                "$ref": "#/components/schemas/Branch"
              }
            },
            "text/json": {
              "schema": {
                "$ref": "#/components/schemas/Branch"
              }
            },
            "application/*+json": {
              "schema": {
                "$ref": "#/components/schemas/Branch"
              }
            }
          }
        },
        "responses": {
          "200": {
            "description": "OK",
            "content": {
              "text/plain": {
                "schema": {
                  "$ref": "#/components/schemas/Branch"
                }
              },
              "application/json": {
                "schema": {
                  "$ref": "#/components/schemas/Branch"
                }
              },
              "text/json": {
                "schema": {
                  "$ref": "#/components/schemas/Branch"
                }
              }
            }
          }
        }
      }
    },
    "/api/Branch/{id}": {
      "get": {
        "tags": [
          "Branch"
        ],
        "parameters": [
          {
            "name": "id",
            "in": "path",
            "required": true,
            "schema": {
              "type": "integer",
              "format": "int32"
            }
          }
        ],
        "responses": {
          "200": {
            "description": "OK",
            "content": {
              "text/plain": {
                "schema": {
                  "$ref": "#/components/schemas/Branch"
                }
              },
              "application/json": {
                "schema": {
                  "$ref": "#/components/schemas/Branch"
                }
              },
              "text/json": {
                "schema": {
                  "$ref": "#/components/schemas/Branch"
                }
              }
            }
          }
        }
      },
      "put": {
        "tags": [
          "Branch"
        ],
        "parameters": [
          {
            "name": "id",
            "in": "path",
            "required": true,
            "schema": {
              "type": "integer",
              "format": "int32"
            }
          }
        ],
        "requestBody": {
          "content": {
            "application/json": {
              "schema": {
                "$ref": "#/components/schemas/Branch"
              }
            },
            "text/json": {
              "schema": {
                "$ref": "#/components/schemas/Branch"
              }
            },
            "application/*+json": {
              "schema": {
                "$ref": "#/components/schemas/Branch"
              }
            }
          }
        },
        "responses": {
          "200": {
            "description": "OK"
          }
        }
      },
      "delete": {
        "tags": [
          "Branch"
        ],
        "parameters": [
          {
            "name": "id",
            "in": "path",
            "required": true,
            "schema": {
              "type": "integer",
              "format": "int32"
            }
          }
        ],
        "responses": {
          "200": {
            "description": "OK"
          }
        }
      }
    },
    "/api/Permission": {
      "get": {
        "tags": [
          "Permission"
        ],
        "responses": {
          "200": {
            "description": "OK",
            "content": {
              "text/plain": {
                "schema": {
                  "type": "array",
                  "items": {
                    "$ref": "#/components/schemas/Permission"
                  }
                }
              },
              "application/json": {
                "schema": {
                  "type": "array",
                  "items": {
                    "$ref": "#/components/schemas/Permission"
                  }
                }
              },
              "text/json": {
                "schema": {
                  "type": "array",
                  "items": {
                    "$ref": "#/components/schemas/Permission"
                  }
                }
              }
            }
          }
        }
      }
    },
    "/api/Permission/{id}": {
      "get": {
        "tags": [
          "Permission"
        ],
        "parameters": [
          {
            "name": "id",
            "in": "path",
            "required": true,
            "schema": {
              "type": "integer",
              "format": "int32"
            }
          }
        ],
        "responses": {
          "200": {
            "description": "OK",
            "content": {
              "text/plain": {
                "schema": {
                  "$ref": "#/components/schemas/Permission"
                }
              },
              "application/json": {
                "schema": {
                  "$ref": "#/components/schemas/Permission"
                }
              },
              "text/json": {
                "schema": {
                  "$ref": "#/components/schemas/Permission"
                }
              }
            }
          }
        }
      }
    },
    "/api/Role": {
      "get": {
        "tags": [
          "Role"
        ],
        "responses": {
          "200": {
            "description": "OK",
            "content": {
              "text/plain": {
                "schema": {
                  "type": "array",
                  "items": {
                    "$ref": "#/components/schemas/Role"
                  }
                }
              },
              "application/json": {
                "schema": {
                  "type": "array",
                  "items": {
                    "$ref": "#/components/schemas/Role"
                  }
                }
              },
              "text/json": {
                "schema": {
                  "type": "array",
                  "items": {
                    "$ref": "#/components/schemas/Role"
                  }
                }
              }
            }
          }
        }
      },
      "post": {
        "tags": [
          "Role"
        ],
        "requestBody": {
          "content": {
            "application/json": {
              "schema": {
                "$ref": "#/components/schemas/Role"
              }
            },
            "text/json": {
              "schema": {
                "$ref": "#/components/schemas/Role"
              }
            },
            "application/*+json": {
              "schema": {
                "$ref": "#/components/schemas/Role"
              }
            }
          }
        },
        "responses": {
          "200": {
            "description": "OK",
            "content": {
              "text/plain": {
                "schema": {
                  "$ref": "#/components/schemas/Role"
                }
              },
              "application/json": {
                "schema": {
                  "$ref": "#/components/schemas/Role"
                }
              },
              "text/json": {
                "schema": {
                  "$ref": "#/components/schemas/Role"
                }
              }
            }
          }
        }
      }
    },
    "/api/Role/{id}": {
      "get": {
        "tags": [
          "Role"
        ],
        "parameters": [
          {
            "name": "id",
            "in": "path",
            "required": true,
            "schema": {
              "type": "integer",
              "format": "int32"
            }
          }
        ],
        "responses": {
          "200": {
            "description": "OK",
            "content": {
              "text/plain": {
                "schema": {
                  "$ref": "#/components/schemas/Role"
                }
              },
              "application/json": {
                "schema": {
                  "$ref": "#/components/schemas/Role"
                }
              },
              "text/json": {
                "schema": {
                  "$ref": "#/components/schemas/Role"
                }
              }
            }
          }
        }
      },
      "put": {
        "tags": [
          "Role"
        ],
        "parameters": [
          {
            "name": "id",
            "in": "path",
            "required": true,
            "schema": {
              "type": "integer",
              "format": "int32"
            }
          }
        ],
        "requestBody": {
          "content": {
            "application/json": {
              "schema": {
                "$ref": "#/components/schemas/Role"
              }
            },
            "text/json": {
              "schema": {
                "$ref": "#/components/schemas/Role"
              }
            },
            "application/*+json": {
              "schema": {
                "$ref": "#/components/schemas/Role"
              }
            }
          }
        },
        "responses": {
          "200": {
            "description": "OK"
          }
        }
      },
      "delete": {
        "tags": [
          "Role"
        ],
        "parameters": [
          {
            "name": "id",
            "in": "path",
            "required": true,
            "schema": {
              "type": "integer",
              "format": "int32"
            }
          }
        ],
        "responses": {
          "200": {
            "description": "OK"
          }
        }
      }
    },
    "/api/Users/create": {
      "post": {
        "tags": [
          "Users"
        ],
        "requestBody": {
          "content": {
            "application/json": {
              "schema": {
                "$ref": "#/components/schemas/UserCreateDto"
              }
            },
            "text/json": {
              "schema": {
                "$ref": "#/components/schemas/UserCreateDto"
              }
            },
            "application/*+json": {
              "schema": {
                "$ref": "#/components/schemas/UserCreateDto"
              }
            }
          }
        },
        "responses": {
          "200": {
            "description": "OK"
          }
        }
      }
    }
  },
  "components": {
    "schemas": {
      "Account": {
        "required": [
          "accountType",
          "bank",
          "branch",
          "currency",
          "status",
          "user"
        ],
        "type": "object",
        "properties": {
          "createdDate": {
            "type": "string",
            "format": "date-time"
          },
          "modifiedDate": {
            "type": "string",
            "format": "date-time",
            "nullable": true
          },
          "createdBy": {
            "type": "string",
            "nullable": true
          },
          "modifiedBy": {
            "type": "string",
            "nullable": true
          },
          "accountNo": {
            "type": "integer",
            "format": "int32"
          },
          "userID": {
            "type": "integer",
            "format": "int32"
          },
          "bankID": {
            "type": "integer",
            "format": "int32"
          },
          "branchID": {
            "type": "integer",
            "format": "int32"
          },
          "accountType": {
            "maxLength": 50,
            "minLength": 0,
            "type": "string"
          },
          "currency": {
            "maxLength": 10,
            "minLength": 0,
            "type": "string"
          },
          "balance": {
            "type": "number",
            "format": "double"
          },
          "status": {
            "maxLength": 20,
            "minLength": 0,
            "type": "string",
            "nullable": true
          },
          "user": {
            "$ref": "#/components/schemas/User"
          },
          "bank": {
            "$ref": "#/components/schemas/Bank"
          },
          "branch": {
            "$ref": "#/components/schemas/Branch"
          },
          "permissions": {
            "type": "array",
            "items": {
              "$ref": "#/components/schemas/Permission"
            },
            "nullable": true
          }
        },
        "additionalProperties": false
      },
      "Bank": {
        "required": [
          "accounts",
          "bankName",
          "branches",
          "headquarters"
        ],
        "type": "object",
        "properties": {
          "createdDate": {
            "type": "string",
            "format": "date-time"
          },
          "modifiedDate": {
            "type": "string",
            "format": "date-time",
            "nullable": true
          },
          "createdBy": {
            "type": "string",
            "nullable": true
          },
          "modifiedBy": {
            "type": "string",
            "nullable": true
          },
          "bankID": {
            "type": "integer",
            "format": "int32"
          },
          "bankName": {
            "maxLength": 100,
            "minLength": 0,
            "type": "string"
          },
          "headquarters": {
            "maxLength": 150,
            "minLength": 0,
            "type": "string",
            "nullable": true
          },
          "establishedYear": {
            "type": "integer",
            "format": "int32",
            "nullable": true
          },
          "branches": {
            "type": "array",
            "items": {
              "$ref": "#/components/schemas/Branch"
            },
            "nullable": true
          },
          "accounts": {
            "type": "array",
            "items": {
              "$ref": "#/components/schemas/Account"
            },
            "nullable": true
          }
        },
        "additionalProperties": false
      },
      "Branch": {
        "required": [
          "accounts",
          "bank",
          "branchName",
          "ifscCode",
          "location"
        ],
        "type": "object",
        "properties": {
          "createdDate": {
            "type": "string",
            "format": "date-time"
          },
          "modifiedDate": {
            "type": "string",
            "format": "date-time",
            "nullable": true
          },
          "createdBy": {
            "type": "string",
            "nullable": true
          },
          "modifiedBy": {
            "type": "string",
            "nullable": true
          },
          "branchID": {
            "type": "integer",
            "format": "int32"
          },
          "bankID": {
            "type": "integer",
            "format": "int32"
          },
          "branchName": {
            "maxLength": 100,
            "minLength": 0,
            "type": "string"
          },
          "location": {
            "maxLength": 150,
            "minLength": 0,
            "type": "string",
            "nullable": true
          },
          "ifscCode": {
            "maxLength": 20,
            "minLength": 0,
            "type": "string",
            "nullable": true
          },
          "bank": {
            "$ref": "#/components/schemas/Bank"
          },
          "accounts": {
            "type": "array",
            "items": {
              "$ref": "#/components/schemas/Account"
            },
            "nullable": true
          }
        },
        "additionalProperties": false
      },
      "LoginRequest": {
        "type": "object",
        "properties": {
          "email": {
            "type": "string",
            "nullable": true
          },
          "password": {
            "type": "string",
            "nullable": true
          }
        },
        "additionalProperties": false
      },
      "Permission": {
        "required": [
          "permissionName"
        ],
        "type": "object",
        "properties": {
          "createdDate": {
            "type": "string",
            "format": "date-time"
          },
          "modifiedDate": {
            "type": "string",
            "format": "date-time",
            "nullable": true
          },
          "createdBy": {
            "type": "string",
            "nullable": true
          },
          "modifiedBy": {
            "type": "string",
            "nullable": true
          },
          "permissionID": {
            "type": "integer",
            "format": "int32"
          },
          "permissionName": {
            "maxLength": 100,
            "minLength": 0,
            "type": "string"
          },
          "description": {
            "maxLength": 150,
            "minLength": 0,
            "type": "string",
            "nullable": true
          }
        },
        "additionalProperties": false
      },
      "Role": {
        "required": [
          "roleName"
        ],
        "type": "object",
        "properties": {
          "createdDate": {
            "type": "string",
            "format": "date-time"
          },
          "modifiedDate": {
            "type": "string",
            "format": "date-time",
            "nullable": true
          },
          "createdBy": {
            "type": "string",
            "nullable": true
          },
          "modifiedBy": {
            "type": "string",
            "nullable": true
          },
          "roleID": {
            "type": "integer",
            "format": "int32"
          },
          "roleName": {
            "maxLength": 50,
            "minLength": 0,
            "type": "string"
          },
          "description": {
            "maxLength": 255,
            "minLength": 0,
            "type": "string",
            "nullable": true
          },
          "userRoles": {
            "type": "array",
            "items": {
              "$ref": "#/components/schemas/UserRole"
            },
            "nullable": true
          }
        },
        "additionalProperties": false
      },
      "User": {
        "required": [
          "email",
          "name",
          "passwordHash"
        ],
        "type": "object",
        "properties": {
          "createdDate": {
            "type": "string",
            "format": "date-time"
          },
          "modifiedDate": {
            "type": "string",
            "format": "date-time",
            "nullable": true
          },
          "createdBy": {
            "type": "string",
            "nullable": true
          },
          "modifiedBy": {
            "type": "string",
            "nullable": true
          },
          "userID": {
            "type": "integer",
            "format": "int32"
          },
          "name": {
            "maxLength": 100,
            "minLength": 0,
            "type": "string"
          },
          "contact": {
            "maxLength": 15,
            "minLength": 0,
            "type": "string",
            "nullable": true
          },
          "email": {
            "maxLength": 100,
            "minLength": 0,
            "type": "string"
          },
          "passwordHash": {
            "maxLength": 255,
            "minLength": 0,
            "type": "string"
          },
          "status": {
            "maxLength": 20,
            "minLength": 0,
            "type": "string",
            "nullable": true
          },
          "userRoles": {
            "type": "array",
            "items": {
              "$ref": "#/components/schemas/UserRole"
            },
            "nullable": true
          }
        },
        "additionalProperties": false
      },
      "UserCreateDto": {
        "required": [
          "email",
          "name",
          "password",
          "roleIds"
        ],
        "type": "object",
        "properties": {
          "name": {
            "type": "string",
            "nullable": true
          },
          "email": {
            "type": "string",
            "nullable": true
          },
          "password": {
            "type": "string",
            "nullable": true
          },
          "roleIds": {
            "type": "array",
            "items": {
              "type": "integer",
              "format": "int32"
            },
            "nullable": true
          }
        },
        "additionalProperties": false
      },
      "UserRole": {
        "type": "object",
        "properties": {
          "userID": {
            "type": "integer",
            "format": "int32"
          },
          "roleID": {
            "type": "integer",
            "format": "int32"
          },
          "user": {
            "$ref": "#/components/schemas/User"
          },
          "role": {
            "$ref": "#/components/schemas/Role"
          }
        },
        "additionalProperties": false
      }
    },
    "securitySchemes": {
      "Bearer": {
        "type": "http",
        "description": "Enter JWT token like: Bearer eyJhbGciOi...",
        "scheme": "Bearer",
        "bearerFormat": "JWT"
      }
    }
  },
  "security": [
    {
      "Bearer": [ ]
    }
  ]
}